annubes/__init__.py
annubes/task.py
annubes/nn/__init__.py
annubes/nn/custom_rnn.py
annubes-0.1.1.dist-info/LICENSE
annubes-0.1.1.dist-info/METADATA
annubes-0.1.1.dist-info/NOTICE
annubes-0.1.1.dist-info/WHEEL
annubes-0.1.1.dist-info/top_level.txt
annubes-0.1.1.dist-info/RECORD
