Metadata-Version: 2.1
Name: annubes
Version: 0.1.1
Summary: ANNUBeS: training Artificial Neural Networks to Uncover Behavioral Strategies in neuroscience
Author-email: Giulia Crocioni <g.crocioni@esciencecenter.nl>, Dani Bodor <d.bodor@esciencecenter.nl>
License: 
Project-URL: Repository, https://github.com/ANNUBS/annubes
Project-URL: Issues, https://github.com/ANNUBS/annubes/issues
Project-URL: Documentation, https://annubs.github.io/annubes
Project-URL: Changelog, https://github.com/ANNUBS/annubes/CHANGELOG.md
Keywords: neuroscience,neural networks
Classifier: Intended Audience :: Developers
Classifier: License :: OSI Approved :: Apache Software License
Classifier: Natural Language :: English
Classifier: Programming Language :: Python :: 3.11
Requires-Python: >=3.11
License-File: LICENSE
License-File: NOTICE
Requires-Dist: numpy >=1.26.2
Requires-Dist: plotly
Requires-Dist: tqdm
Provides-Extra: dev
Requires-Dist: build ; extra == 'dev'
Requires-Dist: bump2version ; extra == 'dev'
Requires-Dist: ruff >=0.3.0 ; extra == 'dev'
Requires-Dist: pytest ; extra == 'dev'
Requires-Dist: pytest-cov ; extra == 'dev'
Requires-Dist: coverage[toml] ; extra == 'dev'
Requires-Dist: mypy ; extra == 'dev'
Requires-Dist: mkdocs ; extra == 'dev'
Requires-Dist: mkdocs-material ; extra == 'dev'
Requires-Dist: mkdocs-exclude ; extra == 'dev'
Requires-Dist: mkdocs-redirects ; extra == 'dev'
Requires-Dist: mkdocstrings-python ; extra == 'dev'
Requires-Dist: mike ; extra == 'dev'
Provides-Extra: publishing
Requires-Dist: build ; extra == 'publishing'
Requires-Dist: twine ; extra == 'publishing'
Requires-Dist: wheel ; extra == 'publishing'
